{"nodes": [{"id": "src_operators_api_jl", "label": "api.jl", "file_type": "code", "source_file": "src/operators/api.jl", "source_location": "L1"}, {"id": "api_staggered_spherical_operators", "label": "staggered_spherical_operators()", "file_type": "code", "source_file": "src/operators/api.jl", "source_location": "L1"}, {"id": "api_validate_staggered", "label": "validate_staggered()", "file_type": "code", "source_file": "src/operators/api.jl", "source_location": "L4"}, {"id": "api_diagnose_staggered", "label": "diagnose_staggered()", "file_type": "code", "source_file": "src/operators/api.jl", "source_location": "L6"}, {"id": "api_interpret_diagnostics_staggered", "label": "interpret_diagnostics_staggered()", "file_type": "code", "source_file": "src/operators/api.jl", "source_location": "L8"}, {"id": "api_non_diagonal_spherical_operators", "label": "non_diagonal_spherical_operators()", "file_type": "code", "source_file": "src/operators/api.jl", "source_location": "L11"}, {"id": "api_apply_even_gradient", "label": "apply_even_gradient()", "file_type": "code", "source_file": "src/operators/api.jl", "source_location": "L14"}, {"id": "api_apply_odd_derivative", "label": "apply_odd_derivative()", "file_type": "code", "source_file": "src/operators/api.jl", "source_location": "L17"}, {"id": "api_apply_divergence", "label": "apply_divergence()", "file_type": "code", "source_file": "src/operators/api.jl", "source_location": "L20"}], "edges": [{"source": "src_operators_api_jl", "target": "api_staggered_spherical_operators", "relation": "defines", "confidence": "EXTRACTED", "source_file": "src/operators/api.jl", "source_location": "L1", "weight": 1.0}, {"source": "src_operators_api_jl", "target": "api_validate_staggered", "relation": "defines", "confidence": "EXTRACTED", "source_file": "src/operators/api.jl", "source_location": "L4", "weight": 1.0}, {"source": "src_operators_api_jl", "target": "api_diagnose_staggered", "relation": "defines", "confidence": "EXTRACTED", "source_file": "src/operators/api.jl", "source_location": "L6", "weight": 1.0}, {"source": "src_operators_api_jl", "target": "api_interpret_diagnostics_staggered", "relation": "defines", "confidence": "EXTRACTED", "source_file": "src/operators/api.jl", "source_location": "L8", "weight": 1.0}, {"source": "src_operators_api_jl", "target": "api_non_diagonal_spherical_operators", "relation": "defines", "confidence": "EXTRACTED", "source_file": "src/operators/api.jl", "source_location": "L11", "weight": 1.0}, {"source": "src_operators_api_jl", "target": "api_apply_even_gradient", "relation": "defines", "confidence": "EXTRACTED", "source_file": "src/operators/api.jl", "source_location": "L14", "weight": 1.0}, {"source": "src_operators_api_jl", "target": "api_apply_odd_derivative", "relation": "defines", "confidence": "EXTRACTED", "source_file": "src/operators/api.jl", "source_location": "L17", "weight": 1.0}, {"source": "src_operators_api_jl", "target": "api_apply_divergence", "relation": "defines", "confidence": "EXTRACTED", "source_file": "src/operators/api.jl", "source_location": "L20", "weight": 1.0}, {"source": "src_operators_api_jl", "target": "api_apply_even_gradient", "relation": "defines", "confidence": "EXTRACTED", "source_file": "src/operators/api.jl", "source_location": "L23", "weight": 1.0}, {"source": "src_operators_api_jl", "target": "api_apply_odd_derivative", "relation": "defines", "confidence": "EXTRACTED", "source_file": "src/operators/api.jl", "source_location": "L24", "weight": 1.0}, {"source": "src_operators_api_jl", "target": "api_apply_divergence", "relation": "defines", "confidence": "EXTRACTED", "source_file": "src/operators/api.jl", "source_location": "L25", "weight": 1.0}, {"source": "api_staggered_spherical_operators", "target": "api_spherical_operators", "relation": "calls", "confidence": "EXTRACTED", "source_file": "src/operators/api.jl", "source_location": "L1", "weight": 1.0}, {"source": "api_validate_staggered", "target": "api_validate", "relation": "calls", "confidence": "EXTRACTED", "source_file": "src/operators/api.jl", "source_location": "L4", "weight": 1.0}, {"source": "api_diagnose_staggered", "target": "api_diagnose", "relation": "calls", "confidence": "EXTRACTED", "source_file": "src/operators/api.jl", "source_location": "L6", "weight": 1.0}, {"source": "api_interpret_diagnostics_staggered", "target": "api_interpret_diagnostics", "relation": "calls", "confidence": "EXTRACTED", "source_file": "src/operators/api.jl", "source_location": "L8", "weight": 1.0}, {"source": "api_non_diagonal_spherical_operators", "target": "api_spherical_operators", "relation": "calls", "confidence": "EXTRACTED", "source_file": "src/operators/api.jl", "source_location": "L11", "weight": 1.0}, {"source": "api_apply_even_gradient", "target": "api_apply_even_gradient", "relation": "calls", "confidence": "EXTRACTED", "source_file": "src/operators/api.jl", "source_location": "L14", "weight": 1.0}, {"source": "api_apply_odd_derivative", "target": "api_apply_odd_derivative", "relation": "calls", "confidence": "EXTRACTED", "source_file": "src/operators/api.jl", "source_location": "L17", "weight": 1.0}, {"source": "api_apply_divergence", "target": "api_apply_divergence", "relation": "calls", "confidence": "EXTRACTED", "source_file": "src/operators/api.jl", "source_location": "L20", "weight": 1.0}]}