{"nodes": [{"id": "src_plots_convergence_jl", "label": "convergence.jl", "file_type": "code", "source_file": "src/plots/convergence.jl", "source_location": "L1"}, {"id": "convergence_extract_wave_solution", "label": "_extract_wave_solution()", "file_type": "code", "source_file": "src/plots/convergence.jl", "source_location": "L1"}, {"id": "convergence_load_glmakie", "label": "_load_glmakie()", "file_type": "code", "source_file": "src/plots/convergence.jl", "source_location": "L5"}, {"id": "convergence_canonical_wave_field", "label": "_canonical_wave_field()", "file_type": "code", "source_file": "src/plots/convergence.jl", "source_location": "L12"}, {"id": "convergence_wave_field_history", "label": "_wave_field_history()", "file_type": "code", "source_file": "src/plots/convergence.jl", "source_location": "L21"}, {"id": "convergence_nested_common_sampling", "label": "_nested_common_sampling()", "file_type": "code", "source_file": "src/plots/convergence.jl", "source_location": "L27"}, {"id": "convergence_validate_nested_vector_alignment", "label": "_validate_nested_vector_alignment()", "file_type": "code", "source_file": "src/plots/convergence.jl", "source_location": "L40"}, {"id": "convergence_error_norm", "label": "_error_norm()", "file_type": "code", "source_file": "src/plots/convergence.jl", "source_location": "L63"}, {"id": "convergence_time_limits_with_padding", "label": "_time_limits_with_padding()", "file_type": "code", "source_file": "src/plots/convergence.jl", "source_location": "L72"}, {"id": "convergence_convergence_order_curve", "label": "_convergence_order_curve()", "file_type": "code", "source_file": "src/plots/convergence.jl", "source_location": "L86"}, {"id": "convergence_pointwise_convergence_order_history", "label": "_pointwise_convergence_order_history()", "file_type": "code", "source_file": "src/plots/convergence.jl", "source_location": "L139"}, {"id": "convergence_finite_limits_with_padding", "label": "_finite_limits_with_padding()", "file_type": "code", "source_file": "src/plots/convergence.jl", "source_location": "L194"}, {"id": "convergence_plot_convergence_order", "label": "plot_convergence_order()", "file_type": "code", "source_file": "src/plots/convergence.jl", "source_location": "L226"}, {"id": "convergence_plot_wave_convergence_orders", "label": "plot_wave_convergence_orders()", "file_type": "code", "source_file": "src/plots/convergence.jl", "source_location": "L265"}, {"id": "convergence_interactive_pointwise_wave_convergence_orders", "label": "interactive_pointwise_wave_convergence_orders()", "file_type": "code", "source_file": "src/plots/convergence.jl", "source_location": "L319"}, {"id": "convergence_interactive_pointwise_wave_convergence_orders_impl", "label": "_interactive_pointwise_wave_convergence_orders_impl()", "file_type": "code", "source_file": "src/plots/convergence.jl", "source_location": "L334"}], "edges": [{"source": "src_plots_convergence_jl", "target": "convergence_extract_wave_solution", "relation": "defines", "confidence": "EXTRACTED", "source_file": "src/plots/convergence.jl", "source_location": "L1", "weight": 1.0}, {"source": "src_plots_convergence_jl", "target": "convergence_load_glmakie", "relation": "defines", "confidence": "EXTRACTED", "source_file": "src/plots/convergence.jl", "source_location": "L5", "weight": 1.0}, {"source": "src_plots_convergence_jl", "target": "convergence_canonical_wave_field", "relation": "defines", "confidence": "EXTRACTED", "source_file": "src/plots/convergence.jl", "source_location": "L12", "weight": 1.0}, {"source": "src_plots_convergence_jl", "target": "convergence_wave_field_history", "relation": "defines", "confidence": "EXTRACTED", "source_file": "src/plots/convergence.jl", "source_location": "L21", "weight": 1.0}, {"source": "src_plots_convergence_jl", "target": "convergence_nested_common_sampling", "relation": "defines", "confidence": "EXTRACTED", "source_file": "src/plots/convergence.jl", "source_location": "L27", "weight": 1.0}, {"source": "src_plots_convergence_jl", "target": "convergence_validate_nested_vector_alignment", "relation": "defines", "confidence": "EXTRACTED", "source_file": "src/plots/convergence.jl", "source_location": "L40", "weight": 1.0}, {"source": "src_plots_convergence_jl", "target": "convergence_error_norm", "relation": "defines", "confidence": "EXTRACTED", "source_file": "src/plots/convergence.jl", "source_location": "L63", "weight": 1.0}, {"source": "src_plots_convergence_jl", "target": "convergence_time_limits_with_padding", "relation": "defines", "confidence": "EXTRACTED", "source_file": "src/plots/convergence.jl", "source_location": "L72", "weight": 1.0}, {"source": "src_plots_convergence_jl", "target": "convergence_convergence_order_curve", "relation": "defines", "confidence": "EXTRACTED", "source_file": "src/plots/convergence.jl", "source_location": "L86", "weight": 1.0}, {"source": "src_plots_convergence_jl", "target": "convergence_pointwise_convergence_order_history", "relation": "defines", "confidence": "EXTRACTED", "source_file": "src/plots/convergence.jl", "source_location": "L139", "weight": 1.0}, {"source": "src_plots_convergence_jl", "target": "convergence_finite_limits_with_padding", "relation": "defines", "confidence": "EXTRACTED", "source_file": "src/plots/convergence.jl", "source_location": "L194", "weight": 1.0}, {"source": "src_plots_convergence_jl", "target": "convergence_plot_convergence_order", "relation": "defines", "confidence": "EXTRACTED", "source_file": "src/plots/convergence.jl", "source_location": "L226", "weight": 1.0}, {"source": "src_plots_convergence_jl", "target": "convergence_plot_wave_convergence_orders", "relation": "defines", "confidence": "EXTRACTED", "source_file": "src/plots/convergence.jl", "source_location": "L265", "weight": 1.0}, {"source": "src_plots_convergence_jl", "target": "convergence_interactive_pointwise_wave_convergence_orders", "relation": "defines", "confidence": "EXTRACTED", "source_file": "src/plots/convergence.jl", "source_location": "L319", "weight": 1.0}, {"source": "src_plots_convergence_jl", "target": "convergence_interactive_pointwise_wave_convergence_orders_impl", "relation": "defines", "confidence": "EXTRACTED", "source_file": "src/plots/convergence.jl", "source_location": "L334", "weight": 1.0}, {"source": "convergence_extract_wave_solution", "target": "convergence_hasproperty", "relation": "calls", "confidence": "EXTRACTED", "source_file": "src/plots/convergence.jl", "source_location": "L2", "weight": 1.0}, {"source": "convergence_extract_wave_solution", "target": "convergence_getproperty", "relation": "calls", "confidence": "EXTRACTED", "source_file": "src/plots/convergence.jl", "source_location": "L2", "weight": 1.0}, {"source": "convergence_load_glmakie", "target": "convergence_isdefined", "relation": "calls", "confidence": "EXTRACTED", "source_file": "src/plots/convergence.jl", "source_location": "L6", "weight": 1.0}, {"source": "convergence_load_glmakie", "target": "convergence_getfield", "relation": "calls", "confidence": "EXTRACTED", "source_file": "src/plots/convergence.jl", "source_location": "L9", "weight": 1.0}, {"source": "convergence_canonical_wave_field", "target": "convergence_throw", "relation": "calls", "confidence": "EXTRACTED", "source_file": "src/plots/convergence.jl", "source_location": "L18", "weight": 1.0}, {"source": "convergence_canonical_wave_field", "target": "convergence_argumenterror", "relation": "calls", "confidence": "EXTRACTED", "source_file": "src/plots/convergence.jl", "source_location": "L18", "weight": 1.0}, {"source": "convergence_wave_field_history", "target": "convergence_extract_wave_solution", "relation": "calls", "confidence": "EXTRACTED", "source_file": "src/plots/convergence.jl", "source_location": "L22", "weight": 1.0}, {"source": "convergence_wave_field_history", "target": "convergence_canonical_wave_field", "relation": "calls", "confidence": "EXTRACTED", "source_file": "src/plots/convergence.jl", "source_location": "L23", "weight": 1.0}, {"source": "convergence_nested_common_sampling", "target": "convergence_throw", "relation": "calls", "confidence": "EXTRACTED", "source_file": "src/plots/convergence.jl", "source_location": "L28", "weight": 1.0}, {"source": "convergence_nested_common_sampling", "target": "convergence_argumenterror", "relation": "calls", "confidence": "EXTRACTED", "source_file": "src/plots/convergence.jl", "source_location": "L28", "weight": 1.0}, {"source": "convergence_nested_common_sampling", "target": "convergence_throw", "relation": "calls", "confidence": "EXTRACTED", "source_file": "src/plots/convergence.jl", "source_location": "L29", "weight": 1.0}, {"source": "convergence_nested_common_sampling", "target": "convergence_argumenterror", "relation": "calls", "confidence": "EXTRACTED", "source_file": "src/plots/convergence.jl", "source_location": "L29", "weight": 1.0}, {"source": "convergence_nested_common_sampling", "target": "convergence_throw", "relation": "calls", "confidence": "EXTRACTED", "source_file": "src/plots/convergence.jl", "source_location": "L30", "weight": 1.0}, {"source": "convergence_nested_common_sampling", "target": "convergence_argumenterror", "relation": "calls", "confidence": "EXTRACTED", "source_file": "src/plots/convergence.jl", "source_location": "L30", "weight": 1.0}, {"source": "convergence_nested_common_sampling", "target": "convergence_min", "relation": "calls", "confidence": "EXTRACTED", "source_file": "src/plots/convergence.jl", "source_location": "L32", "weight": 1.0}, {"source": "convergence_nested_common_sampling", "target": "convergence_fld", "relation": "calls", "confidence": "EXTRACTED", "source_file": "src/plots/convergence.jl", "source_location": "L32", "weight": 1.0}, {"source": "convergence_nested_common_sampling", "target": "convergence_fld", "relation": "calls", "confidence": "EXTRACTED", "source_file": "src/plots/convergence.jl", "source_location": "L32", "weight": 1.0}, {"source": "convergence_nested_common_sampling", "target": "convergence_throw", "relation": "calls", "confidence": "EXTRACTED", "source_file": "src/plots/convergence.jl", "source_location": "L33", "weight": 1.0}, {"source": "convergence_nested_common_sampling", "target": "convergence_argumenterror", "relation": "calls", "confidence": "EXTRACTED", "source_file": "src/plots/convergence.jl", "source_location": "L33", "weight": 1.0}, {"source": "convergence_nested_common_sampling", "target": "convergence_collect", "relation": "calls", "confidence": "EXTRACTED", "source_file": "src/plots/convergence.jl", "source_location": "L35", "weight": 1.0}, {"source": "convergence_nested_common_sampling", "target": "convergence_collect", "relation": "calls", "confidence": "EXTRACTED", "source_file": "src/plots/convergence.jl", "source_location": "L36", "weight": 1.0}, {"source": "convergence_nested_common_sampling", "target": "convergence_collect", "relation": "calls", "confidence": "EXTRACTED", "source_file": "src/plots/convergence.jl", "source_location": "L37", "weight": 1.0}, {"source": "convergence_validate_nested_vector_alignment", "target": "convergence_maximum", "relation": "calls", "confidence": "EXTRACTED", "source_file": "src/plots/convergence.jl", "source_location": "L51", "weight": 1.0}, {"source": "convergence_validate_nested_vector_alignment", "target": "convergence_vcat", "relation": "calls", "confidence": "EXTRACTED", "source_file": "src/plots/convergence.jl", "source_location": "L51", "weight": 1.0}, {"source": "convergence_validate_nested_vector_alignment", "target": "convergence_max", "relation": "calls", "confidence": "EXTRACTED", "source_file": "src/plots/convergence.jl", "source_location": "L52", "weight": 1.0}, {"source": "convergence_validate_nested_vector_alignment", "target": "convergence_float64", "relation": "calls", "confidence": "EXTRACTED", "source_file": "src/plots/convergence.jl", "source_location": "L52", "weight": 1.0}, {"source": "convergence_validate_nested_vector_alignment", "target": "convergence_float64", "relation": "calls", "confidence": "EXTRACTED", "source_file": "src/plots/convergence.jl", "source_location": "L52", "weight": 1.0}, {"source": "convergence_validate_nested_vector_alignment", "target": "convergence_max", "relation": "calls", "confidence": "EXTRACTED", "source_file": "src/plots/convergence.jl", "source_location": "L52", "weight": 1.0}, {"source": "convergence_validate_nested_vector_alignment", "target": "convergence_max", "relation": "calls", "confidence": "EXTRACTED", "source_file": "src/plots/convergence.jl", "source_location": "L54", "weight": 1.0}, {"source": "convergence_validate_nested_vector_alignment", "target": "convergence_isempty", "relation": "calls", "confidence": "EXTRACTED", "source_file": "src/plots/convergence.jl", "source_location": "L54", "weight": 1.0}, {"source": "convergence_validate_nested_vector_alignment", "target": "convergence_maximum", "relation": "calls", "confidence": "EXTRACTED", "source_file": "src/plots/convergence.jl", "source_location": "L54", "weight": 1.0}, {"source": "convergence_validate_nested_vector_alignment", "target": "convergence_isempty", "relation": "calls", "confidence": "EXTRACTED", "source_file": "src/plots/convergence.jl", "source_location": "L55", "weight": 1.0}, {"source": "convergence_validate_nested_vector_alignment", "target": "convergence_maximum", "relation": "calls", "confidence": "EXTRACTED", "source_file": "src/plots/convergence.jl", "source_location": "L55", "weight": 1.0}, {"source": "convergence_validate_nested_vector_alignment", "target": "convergence_throw", "relation": "calls", "confidence": "EXTRACTED", "source_file": "src/plots/convergence.jl", "source_location": "L58", "weight": 1.0}, {"source": "convergence_validate_nested_vector_alignment", "target": "convergence_argumenterror", "relation": "calls", "confidence": "EXTRACTED", "source_file": "src/plots/convergence.jl", "source_location": "L58", "weight": 1.0}, {"source": "convergence_error_norm", "target": "convergence_norm", "relation": "calls", "confidence": "EXTRACTED", "source_file": "src/plots/convergence.jl", "source_location": "L65", "weight": 1.0}, {"source": "convergence_error_norm", "target": "convergence_sqrt", "relation": "calls", "confidence": "EXTRACTED", "source_file": "src/plots/convergence.jl", "source_location": "L65", "weight": 1.0}, {"source": "convergence_error_norm", "target": "convergence_length", "relation": "calls", "confidence": "EXTRACTED", "source_file": "src/plots/convergence.jl", "source_location": "L65", "weight": 1.0}, {"source": "convergence_error_norm", "target": "convergence_maximum", "relation": "calls", "confidence": "EXTRACTED", "source_file": "src/plots/convergence.jl", "source_location": "L67", "weight": 1.0}, {"source": "convergence_error_norm", "target": "convergence_throw", "relation": "calls", "confidence": "EXTRACTED", "source_file": "src/plots/convergence.jl", "source_location": "L69", "weight": 1.0}, {"source": "convergence_error_norm", "target": "convergence_argumenterror", "relation": "calls", "confidence": "EXTRACTED", "source_file": "src/plots/convergence.jl", "source_location": "L69", "weight": 1.0}, {"source": "convergence_time_limits_with_padding", "target": "convergence_isempty", "relation": "calls", "confidence": "EXTRACTED", "source_file": "src/plots/convergence.jl", "source_location": "L76", "weight": 1.0}, {"source": "convergence_time_limits_with_padding", "target": "convergence_throw", "relation": "calls", "confidence": "EXTRACTED", "source_file": "src/plots/convergence.jl", "source_location": "L76", "weight": 1.0}, {"source": "convergence_time_limits_with_padding", "target": "convergence_argumenterror", "relation": "calls", "confidence": "EXTRACTED", "source_file": "src/plots/convergence.jl", "source_location": "L76", "weight": 1.0}, {"source": "convergence_time_limits_with_padding", "target": "convergence_extrema", "relation": "calls", "confidence": "EXTRACTED", "source_file": "src/plots/convergence.jl", "source_location": "L78", "weight": 1.0}, {"source": "convergence_time_limits_with_padding", "target": "convergence_max", "relation": "calls", "confidence": "EXTRACTED", "source_file": "src/plots/convergence.jl", "source_location": "L80", "weight": 1.0}, {"source": "convergence_time_limits_with_padding", "target": "convergence_abs", "relation": "calls", "confidence": "EXTRACTED", "source_file": "src/plots/convergence.jl", "source_location": "L80", "weight": 1.0}, {"source": "convergence_time_limits_with_padding", "target": "convergence_abs", "relation": "calls", "confidence": "EXTRACTED", "source_file": "src/plots/convergence.jl", "source_location": "L80", "weight": 1.0}, {"source": "convergence_convergence_order_curve", "target": "convergence_extract_wave_solution", "relation": "calls", "confidence": "EXTRACTED", "source_file": "src/plots/convergence.jl", "source_location": "L91", "weight": 1.0}, {"source": "convergence_convergence_order_curve", "target": "convergence_extract_wave_solution", "relation": "calls", "confidence": "EXTRACTED", "source_file": "src/plots/convergence.jl", "source_location": "L92", "weight": 1.0}, {"source": "convergence_convergence_order_curve", "target": "convergence_extract_wave_solution", "relation": "calls", "confidence": "EXTRACTED", "source_file": "src/plots/convergence.jl", "source_location": "L93", "weight": 1.0}, {"source": "convergence_convergence_order_curve", "target": "convergence_nested_common_sampling", "relation": "calls", "confidence": "EXTRACTED", "source_file": "src/plots/convergence.jl", "source_location": "L95", "weight": 1.0}, {"source": "convergence_convergence_order_curve", "target": "convergence_length", "relation": "calls", "confidence": "EXTRACTED", "source_file": "src/plots/convergence.jl", "source_location": "L95", "weight": 1.0}, {"source": "convergence_convergence_order_curve", "target": "convergence_length", "relation": "calls", "confidence": "EXTRACTED", "source_file": "src/plots/convergence.jl", "source_location": "L95", "weight": 1.0}, {"source": "convergence_convergence_order_curve", "target": "convergence_length", "relation": "calls", "confidence": "EXTRACTED", "source_file": "src/plots/convergence.jl", "source_location": "L96", "weight": 1.0}, {"source": "convergence_convergence_order_curve", "target": "convergence_nested_common_sampling", "relation": "calls", "confidence": "EXTRACTED", "source_file": "src/plots/convergence.jl", "source_location": "L97", "weight": 1.0}, {"source": "convergence_convergence_order_curve", "target": "convergence_length", "relation": "calls", "confidence": "EXTRACTED", "source_file": "src/plots/convergence.jl", "source_location": "L97", "weight": 1.0}, {"source": "convergence_convergence_order_curve", "target": "convergence_length", "relation": "calls", "confidence": "EXTRACTED", "source_file": "src/plots/convergence.jl", "source_location": "L97", "weight": 1.0}, {"source": "convergence_convergence_order_curve", "target": "convergence_length", "relation": "calls", "confidence": "EXTRACTED", "source_file": "src/plots/convergence.jl", "source_location": "L98", "weight": 1.0}, {"source": "convergence_convergence_order_curve", "target": "convergence_validate_nested_vector_alignment", "relation": "calls", "confidence": "EXTRACTED", "source_file": "src/plots/convergence.jl", "source_location": "L100", "weight": 1.0}, {"source": "convergence_convergence_order_curve", "target": "convergence_validate_nested_vector_alignment", "relation": "calls", "confidence": "EXTRACTED", "source_file": "src/plots/convergence.jl", "source_location": "L102", "weight": 1.0}, {"source": "convergence_convergence_order_curve", "target": "convergence_wave_field_history", "relation": "calls", "confidence": "EXTRACTED", "source_file": "src/plots/convergence.jl", "source_location": "L106", "weight": 1.0}, {"source": "convergence_convergence_order_curve", "target": "convergence_wave_field_history", "relation": "calls", "confidence": "EXTRACTED", "source_file": "src/plots/convergence.jl", "source_location": "L107", "weight": 1.0}, {"source": "convergence_convergence_order_curve", "target": "convergence_wave_field_history", "relation": "calls", "confidence": "EXTRACTED", "source_file": "src/plots/convergence.jl", "source_location": "L108", "weight": 1.0}, {"source": "convergence_convergence_order_curve", "target": "convergence_fill", "relation": "calls", "confidence": "EXTRACTED", "source_file": "src/plots/convergence.jl", "source_location": "L110", "weight": 1.0}, {"source": "convergence_convergence_order_curve", "target": "convergence_length", "relation": "calls", "confidence": "EXTRACTED", "source_file": "src/plots/convergence.jl", "source_location": "L110", "weight": 1.0}, {"source": "convergence_convergence_order_curve", "target": "convergence_zeros", "relation": "calls", "confidence": "EXTRACTED", "source_file": "src/plots/convergence.jl", "source_location": "L111", "weight": 1.0}, {"source": "convergence_convergence_order_curve", "target": "convergence_length", "relation": "calls", "confidence": "EXTRACTED", "source_file": "src/plots/convergence.jl", "source_location": "L111", "weight": 1.0}, {"source": "convergence_convergence_order_curve", "target": "convergence_zeros", "relation": "calls", "confidence": "EXTRACTED", "source_file": "src/plots/convergence.jl", "source_location": "L112", "weight": 1.0}, {"source": "convergence_convergence_order_curve", "target": "convergence_length", "relation": "calls", "confidence": "EXTRACTED", "source_file": "src/plots/convergence.jl", "source_location": "L112", "weight": 1.0}, {"source": "convergence_convergence_order_curve", "target": "convergence_eachindex", "relation": "calls", "confidence": "EXTRACTED", "source_file": "src/plots/convergence.jl", "source_location": "L114", "weight": 1.0}, {"source": "convergence_convergence_order_curve", "target": "convergence_error_norm", "relation": "calls", "confidence": "EXTRACTED", "source_file": "src/plots/convergence.jl", "source_location": "L122", "weight": 1.0}, {"source": "convergence_convergence_order_curve", "target": "convergence_error_norm", "relation": "calls", "confidence": "EXTRACTED", "source_file": "src/plots/convergence.jl", "source_location": "L123", "weight": 1.0}, {"source": "convergence_convergence_order_curve", "target": "convergence_log2", "relation": "calls", "confidence": "EXTRACTED", "source_file": "src/plots/convergence.jl", "source_location": "L126", "weight": 1.0}, {"source": "convergence_convergence_order_curve", "target": "convergence_canonical_wave_field", "relation": "calls", "confidence": "EXTRACTED", "source_file": "src/plots/convergence.jl", "source_location": "L135", "weight": 1.0}, {"source": "convergence_pointwise_convergence_order_history", "target": "convergence_extract_wave_solution", "relation": "calls", "confidence": "EXTRACTED", "source_file": "src/plots/convergence.jl", "source_location": "L143", "weight": 1.0}, {"source": "convergence_pointwise_convergence_order_history", "target": "convergence_extract_wave_solution", "relation": "calls", "confidence": "EXTRACTED", "source_file": "src/plots/convergence.jl", "source_location": "L144", "weight": 1.0}, {"source": "convergence_pointwise_convergence_order_history", "target": "convergence_extract_wave_solution", "relation": "calls", "confidence": "EXTRACTED", "source_file": "src/plots/convergence.jl", "source_location": "L145", "weight": 1.0}, {"source": "convergence_pointwise_convergence_order_history", "target": "convergence_nested_common_sampling", "relation": "calls", "confidence": "EXTRACTED", "source_file": "src/plots/convergence.jl", "source_location": "L147", "weight": 1.0}, {"source": "convergence_pointwise_convergence_order_history", "target": "convergence_length", "relation": "calls", "confidence": "EXTRACTED", "source_file": "src/plots/convergence.jl", "source_location": "L147", "weight": 1.0}, {"source": "convergence_pointwise_convergence_order_history", "target": "convergence_length", "relation": "calls", "confidence": "EXTRACTED", "source_file": "src/plots/convergence.jl", "source_location": "L147", "weight": 1.0}, {"source": "convergence_pointwise_convergence_order_history", "target": "convergence_length", "relation": "calls", "confidence": "EXTRACTED", "source_file": "src/plots/convergence.jl", "source_location": "L148", "weight": 1.0}, {"source": "convergence_pointwise_convergence_order_history", "target": "convergence_nested_common_sampling", "relation": "calls", "confidence": "EXTRACTED", "source_file": "src/plots/convergence.jl", "source_location": "L149", "weight": 1.0}, {"source": "convergence_pointwise_convergence_order_history", "target": "convergence_length", "relation": "calls", "confidence": "EXTRACTED", "source_file": "src/plots/convergence.jl", "source_location": "L149", "weight": 1.0}, {"source": "convergence_pointwise_convergence_order_history", "target": "convergence_length", "relation": "calls", "confidence": "EXTRACTED", "source_file": "src/plots/convergence.jl", "source_location": "L149", "weight": 1.0}, {"source": "convergence_pointwise_convergence_order_history", "target": "convergence_length", "relation": "calls", "confidence": "EXTRACTED", "source_file": "src/plots/convergence.jl", "source_location": "L150", "weight": 1.0}, {"source": "convergence_pointwise_convergence_order_history", "target": "convergence_validate_nested_vector_alignment", "relation": "calls", "confidence": "EXTRACTED", "source_file": "src/plots/convergence.jl", "source_location": "L152", "weight": 1.0}, {"source": "convergence_pointwise_convergence_order_history", "target": "convergence_validate_nested_vector_alignment", "relation": "calls", "confidence": "EXTRACTED", "source_file": "src/plots/convergence.jl", "source_location": "L154", "weight": 1.0}, {"source": "convergence_pointwise_convergence_order_history", "target": "convergence_wave_field_history", "relation": "calls", "confidence": "EXTRACTED", "source_file": "src/plots/convergence.jl", "source_location": "L158", "weight": 1.0}, {"source": "convergence_pointwise_convergence_order_history", "target": "convergence_wave_field_history", "relation": "calls", "confidence": "EXTRACTED", "source_file": "src/plots/convergence.jl", "source_location": "L159", "weight": 1.0}, {"source": "convergence_pointwise_convergence_order_history", "target": "convergence_wave_field_history", "relation": "calls", "confidence": "EXTRACTED", "source_file": "src/plots/convergence.jl", "source_location": "L160", "weight": 1.0}, {"source": "convergence_pointwise_convergence_order_history", "target": "convergence_length", "relation": "calls", "confidence": "EXTRACTED", "source_file": "src/plots/convergence.jl", "source_location": "L162", "weight": 1.0}, {"source": "convergence_pointwise_convergence_order_history", "target": "convergence_length", "relation": "calls", "confidence": "EXTRACTED", "source_file": "src/plots/convergence.jl", "source_location": "L163", "weight": 1.0}, {"source": "convergence_pointwise_convergence_order_history", "target": "convergence_fill", "relation": "calls", "confidence": "EXTRACTED", "source_file": "src/plots/convergence.jl", "source_location": "L164", "weight": 1.0}, {"source": "convergence_pointwise_convergence_order_history", "target": "convergence_fill", "relation": "calls", "confidence": "EXTRACTED", "source_file": "src/plots/convergence.jl", "source_location": "L165", "weight": 1.0}, {"source": "convergence_pointwise_convergence_order_history", "target": "convergence_fill", "relation": "calls", "confidence": "EXTRACTED", "source_file": "src/plots/convergence.jl", "source_location": "L166", "weight": 1.0}, {"source": "convergence_pointwise_convergence_order_history", "target": "convergence_eachindex", "relation": "calls", "confidence": "EXTRACTED", "source_file": "src/plots/convergence.jl", "source_location": "L168", "weight": 1.0}, {"source": "convergence_pointwise_convergence_order_history", "target": "convergence_eachindex", "relation": "calls", "confidence": "EXTRACTED", "source_file": "src/plots/convergence.jl", "source_location": "L179", "weight": 1.0}, {"source": "convergence_pointwise_convergence_order_history", "target": "convergence_log2", "relation": "calls", "confidence": "EXTRACTED", "source_file": "src/plots/convergence.jl", "source_location": "L181", "weight": 1.0}, {"source": "convergence_pointwise_convergence_order_history", "target": "convergence_canonical_wave_field", "relation": "calls", "confidence": "EXTRACTED", "source_file": "src/plots/convergence.jl", "source_location": "L191", "weight": 1.0}, {"source": "convergence_finite_limits_with_padding", "target": "convergence_float64", "relation": "calls", "confidence": "EXTRACTED", "source_file": "src/plots/convergence.jl", "source_location": "L199", "weight": 1.0}, {"source": "convergence_finite_limits_with_padding", "target": "convergence_isfinite", "relation": "calls", "confidence": "EXTRACTED", "source_file": "src/plots/convergence.jl", "source_location": "L200", "weight": 1.0}, {"source": "convergence_finite_limits_with_padding", "target": "convergence_push", "relation": "calls", "confidence": "EXTRACTED", "source_file": "src/plots/convergence.jl", "source_location": "L200", "weight": 1.0}, {"source": "convergence_finite_limits_with_padding", "target": "convergence_isempty", "relation": "calls", "confidence": "EXTRACTED", "source_file": "src/plots/convergence.jl", "source_location": "L203", "weight": 1.0}, {"source": "convergence_finite_limits_with_padding", "target": "convergence_extrema", "relation": "calls", "confidence": "EXTRACTED", "source_file": "src/plots/convergence.jl", "source_location": "L205", "weight": 1.0}, {"source": "convergence_finite_limits_with_padding", "target": "convergence_max", "relation": "calls", "confidence": "EXTRACTED", "source_file": "src/plots/convergence.jl", "source_location": "L207", "weight": 1.0}, {"source": "convergence_finite_limits_with_padding", "target": "convergence_abs", "relation": "calls", "confidence": "EXTRACTED", "source_file": "src/plots/convergence.jl", "source_location": "L207", "weight": 1.0}, {"source": "convergence_finite_limits_with_padding", "target": "convergence_abs", "relation": "calls", "confidence": "EXTRACTED", "source_file": "src/plots/convergence.jl", "source_location": "L207", "weight": 1.0}, {"source": "convergence_finite_limits_with_padding", "target": "convergence_max", "relation": "calls", "confidence": "EXTRACTED", "source_file": "src/plots/convergence.jl", "source_location": "L208", "weight": 1.0}, {"source": "convergence_finite_limits_with_padding", "target": "convergence_float64", "relation": "calls", "confidence": "EXTRACTED", "source_file": "src/plots/convergence.jl", "source_location": "L208", "weight": 1.0}, {"source": "convergence_finite_limits_with_padding", "target": "convergence_float64", "relation": "calls", "confidence": "EXTRACTED", "source_file": "src/plots/convergence.jl", "source_location": "L208", "weight": 1.0}, {"source": "convergence_plot_convergence_order", "target": "convergence_convergence_order_curve", "relation": "calls", "confidence": "EXTRACTED", "source_file": "src/plots/convergence.jl", "source_location": "L232", "weight": 1.0}, {"source": "convergence_plot_convergence_order", "target": "convergence_isnothing", "relation": "calls", "confidence": "EXTRACTED", "source_file": "src/plots/convergence.jl", "source_location": "L237", "weight": 1.0}, {"source": "convergence_plot_convergence_order", "target": "convergence_latexstring", "relation": "calls", "confidence": "EXTRACTED", "source_file": "src/plots/convergence.jl", "source_location": "L238", "weight": 1.0}, {"source": "convergence_plot_convergence_order", "target": "convergence_with_spectrum_theme", "relation": "calls", "confidence": "EXTRACTED", "source_file": "src/plots/convergence.jl", "source_location": "L244", "weight": 1.0}, {"source": "convergence_plot_convergence_order", "target": "convergence_figure", "relation": "calls", "confidence": "EXTRACTED", "source_file": "src/plots/convergence.jl", "source_location": "L245", "weight": 1.0}, {"source": "convergence_plot_convergence_order", "target": "convergence_axis", "relation": "calls", "confidence": "EXTRACTED", "source_file": "src/plots/convergence.jl", "source_location": "L246", "weight": 1.0}, {"source": "convergence_plot_convergence_order", "target": "convergence_lines", "relation": "calls", "confidence": "EXTRACTED", "source_file": "src/plots/convergence.jl", "source_location": "L250", "weight": 1.0}, {"source": "convergence_plot_convergence_order", "target": "convergence_xlims", "relation": "calls", "confidence": "EXTRACTED", "source_file": "src/plots/convergence.jl", "source_location": "L252", "weight": 1.0}, {"source": "convergence_plot_convergence_order", "target": "convergence_time_limits_with_padding", "relation": "calls", "confidence": "EXTRACTED", "source_file": "src/plots/convergence.jl", "source_location": "L252", "weight": 1.0}, {"source": "convergence_plot_wave_convergence_orders", "target": "convergence_convergence_order_curve", "relation": "calls", "confidence": "EXTRACTED", "source_file": "src/plots/convergence.jl", "source_location": "L269", "weight": 1.0}, {"source": "convergence_plot_wave_convergence_orders", "target": "convergence_convergence_order_curve", "relation": "calls", "confidence": "EXTRACTED", "source_file": "src/plots/convergence.jl", "source_location": "L272", "weight": 1.0}, {"source": "convergence_plot_wave_convergence_orders", "target": "convergence_with_spectrum_theme", "relation": "calls", "confidence": "EXTRACTED", "source_file": "src/plots/convergence.jl", "source_location": "L280", "weight": 1.0}, {"source": "convergence_plot_wave_convergence_orders", "target": "convergence_figure", "relation": "calls", "confidence": "EXTRACTED", "source_file": "src/plots/convergence.jl", "source_location": "L281", "weight": 1.0}, {"source": "convergence_plot_wave_convergence_orders", "target": "convergence_axis", "relation": "calls", "confidence": "EXTRACTED", "source_file": "src/plots/convergence.jl", "source_location": "L283", "weight": 1.0}, {"source": "convergence_plot_wave_convergence_orders", "target": "convergence_lines", "relation": "calls", "confidence": "EXTRACTED", "source_file": "src/plots/convergence.jl", "source_location": "L287", "weight": 1.0}, {"source": "convergence_plot_wave_convergence_orders", "target": "convergence_scatter", "relation": "calls", "confidence": "EXTRACTED", "source_file": "src/plots/convergence.jl", "source_location": "L288", "weight": 1.0}, {"source": "convergence_plot_wave_convergence_orders", "target": "convergence_xlims", "relation": "calls", "confidence": "EXTRACTED", "source_file": "src/plots/convergence.jl", "source_location": "L289", "weight": 1.0}, {"source": "convergence_plot_wave_convergence_orders", "target": "convergence_time_limits_with_padding", "relation": "calls", "confidence": "EXTRACTED", "source_file": "src/plots/convergence.jl", "source_location": "L289", "weight": 1.0}, {"source": "convergence_plot_wave_convergence_orders", "target": "convergence_axis", "relation": "calls", "confidence": "EXTRACTED", "source_file": "src/plots/convergence.jl", "source_location": "L291", "weight": 1.0}, {"source": "convergence_plot_wave_convergence_orders", "target": "convergence_lines", "relation": "calls", "confidence": "EXTRACTED", "source_file": "src/plots/convergence.jl", "source_location": "L295", "weight": 1.0}, {"source": "convergence_plot_wave_convergence_orders", "target": "convergence_scatter", "relation": "calls", "confidence": "EXTRACTED", "source_file": "src/plots/convergence.jl", "source_location": "L296", "weight": 1.0}, {"source": "convergence_plot_wave_convergence_orders", "target": "convergence_xlims", "relation": "calls", "confidence": "EXTRACTED", "source_file": "src/plots/convergence.jl", "source_location": "L297", "weight": 1.0}, {"source": "convergence_plot_wave_convergence_orders", "target": "convergence_time_limits_with_padding", "relation": "calls", "confidence": "EXTRACTED", "source_file": "src/plots/convergence.jl", "source_location": "L297", "weight": 1.0}, {"source": "convergence_interactive_pointwise_wave_convergence_orders", "target": "convergence_invokelatest", "relation": "calls", "confidence": "EXTRACTED", "source_file": "src/plots/convergence.jl", "source_location": "L324", "weight": 1.0}, {"source": "convergence_interactive_pointwise_wave_convergence_orders", "target": "convergence_invokelatest", "relation": "calls", "confidence": "EXTRACTED", "source_file": "src/plots/convergence.jl", "source_location": "L325", "weight": 1.0}, {"source": "convergence_interactive_pointwise_wave_convergence_orders_impl", "target": "convergence_pointwise_convergence_order_history", "relation": "calls", "confidence": "EXTRACTED", "source_file": "src/plots/convergence.jl", "source_location": "L340", "weight": 1.0}, {"source": "convergence_interactive_pointwise_wave_convergence_orders_impl", "target": "convergence_pointwise_convergence_order_history", "relation": "calls", "confidence": "EXTRACTED", "source_file": "src/plots/convergence.jl", "source_location": "L342", "weight": 1.0}, {"source": "convergence_interactive_pointwise_wave_convergence_orders_impl", "target": "convergence_length", "relation": "calls", "confidence": "EXTRACTED", "source_file": "src/plots/convergence.jl", "source_location": "L345", "weight": 1.0}, {"source": "convergence_interactive_pointwise_wave_convergence_orders_impl", "target": "convergence_throw", "relation": "calls", "confidence": "EXTRACTED", "source_file": "src/plots/convergence.jl", "source_location": "L347", "weight": 1.0}, {"source": "convergence_interactive_pointwise_wave_convergence_orders_impl", "target": "convergence_argumenterror", "relation": "calls", "confidence": "EXTRACTED", "source_file": "src/plots/convergence.jl", "source_location": "L347", "weight": 1.0}, {"source": "convergence_interactive_pointwise_wave_convergence_orders_impl", "target": "convergence_activate", "relation": "calls", "confidence": "EXTRACTED", "source_file": "src/plots/convergence.jl", "source_location": "L349", "weight": 1.0}, {"source": "convergence_interactive_pointwise_wave_convergence_orders_impl", "target": "convergence_with_theme", "relation": "calls", "confidence": "EXTRACTED", "source_file": "src/plots/convergence.jl", "source_location": "L352", "weight": 1.0}, {"source": "convergence_interactive_pointwise_wave_convergence_orders_impl", "target": "convergence_mytheme_aps", "relation": "calls", "confidence": "EXTRACTED", "source_file": "src/plots/convergence.jl", "source_location": "L352", "weight": 1.0}, {"source": "convergence_interactive_pointwise_wave_convergence_orders_impl", "target": "convergence_figure", "relation": "calls", "confidence": "EXTRACTED", "source_file": "src/plots/convergence.jl", "source_location": "L353", "weight": 1.0}, {"source": "convergence_interactive_pointwise_wave_convergence_orders_impl", "target": "convergence_label", "relation": "calls", "confidence": "EXTRACTED", "source_file": "src/plots/convergence.jl", "source_location": "L355", "weight": 1.0}, {"source": "convergence_interactive_pointwise_wave_convergence_orders_impl", "target": "convergence_axis", "relation": "calls", "confidence": "EXTRACTED", "source_file": "src/plots/convergence.jl", "source_location": "L360", "weight": 1.0}, {"source": "convergence_interactive_pointwise_wave_convergence_orders_impl", "target": "convergence_axis", "relation": "calls", "confidence": "EXTRACTED", "source_file": "src/plots/convergence.jl", "source_location": "L364", "weight": 1.0}, {"source": "convergence_interactive_pointwise_wave_convergence_orders_impl", "target": "convergence_hlines", "relation": "calls", "confidence": "EXTRACTED", "source_file": "src/plots/convergence.jl", "source_location": "L370", "weight": 1.0}, {"source": "convergence_interactive_pointwise_wave_convergence_orders_impl", "target": "convergence_xlims", "relation": "calls", "confidence": "EXTRACTED", "source_file": "src/plots/convergence.jl", "source_location": "L371", "weight": 1.0}, {"source": "convergence_interactive_pointwise_wave_convergence_orders_impl", "target": "convergence_minimum", "relation": "calls", "confidence": "EXTRACTED", "source_file": "src/plots/convergence.jl", "source_location": "L371", "weight": 1.0}, {"source": "convergence_interactive_pointwise_wave_convergence_orders_impl", "target": "convergence_maximum", "relation": "calls", "confidence": "EXTRACTED", "source_file": "src/plots/convergence.jl", "source_location": "L371", "weight": 1.0}, {"source": "convergence_interactive_pointwise_wave_convergence_orders_impl", "target": "convergence_ylims", "relation": "calls", "confidence": "EXTRACTED", "source_file": "src/plots/convergence.jl", "source_location": "L372", "weight": 1.0}, {"source": "convergence_interactive_pointwise_wave_convergence_orders_impl", "target": "convergence_slider", "relation": "calls", "confidence": "EXTRACTED", "source_file": "src/plots/convergence.jl", "source_location": "L375", "weight": 1.0}, {"source": "convergence_interactive_pointwise_wave_convergence_orders_impl", "target": "convergence_lift", "relation": "calls", "confidence": "EXTRACTED", "source_file": "src/plots/convergence.jl", "source_location": "L381", "weight": 1.0}, {"source": "convergence_interactive_pointwise_wave_convergence_orders_impl", "target": "convergence_latexstring", "relation": "calls", "confidence": "EXTRACTED", "source_file": "src/plots/convergence.jl", "source_location": "L382", "weight": 1.0}, {"source": "convergence_interactive_pointwise_wave_convergence_orders_impl", "target": "convergence_float64", "relation": "calls", "confidence": "EXTRACTED", "source_file": "src/plots/convergence.jl", "source_location": "L382", "weight": 1.0}, {"source": "convergence_interactive_pointwise_wave_convergence_orders_impl", "target": "convergence_string", "relation": "calls", "confidence": "EXTRACTED", "source_file": "src/plots/convergence.jl", "source_location": "L383", "weight": 1.0}, {"source": "convergence_interactive_pointwise_wave_convergence_orders_impl", "target": "convergence_string", "relation": "calls", "confidence": "EXTRACTED", "source_file": "src/plots/convergence.jl", "source_location": "L383", "weight": 1.0}, {"source": "convergence_interactive_pointwise_wave_convergence_orders_impl", "target": "convergence_label", "relation": "calls", "confidence": "EXTRACTED", "source_file": "src/plots/convergence.jl", "source_location": "L385", "weight": 1.0}, {"source": "convergence_interactive_pointwise_wave_convergence_orders_impl", "target": "convergence_lift", "relation": "calls", "confidence": "EXTRACTED", "source_file": "src/plots/convergence.jl", "source_location": "L387", "weight": 1.0}, {"source": "convergence_interactive_pointwise_wave_convergence_orders_impl", "target": "convergence_lift", "relation": "calls", "confidence": "EXTRACTED", "source_file": "src/plots/convergence.jl", "source_location": "L388", "weight": 1.0}, {"source": "convergence_interactive_pointwise_wave_convergence_orders_impl", "target": "convergence_lines", "relation": "calls", "confidence": "EXTRACTED", "source_file": "src/plots/convergence.jl", "source_location": "L390", "weight": 1.0}, {"source": "convergence_interactive_pointwise_wave_convergence_orders_impl", "target": "convergence_scatter", "relation": "calls", "confidence": "EXTRACTED", "source_file": "src/plots/convergence.jl", "source_location": "L391", "weight": 1.0}, {"source": "convergence_interactive_pointwise_wave_convergence_orders_impl", "target": "convergence_lines", "relation": "calls", "confidence": "EXTRACTED", "source_file": "src/plots/convergence.jl", "source_location": "L393", "weight": 1.0}, {"source": "convergence_interactive_pointwise_wave_convergence_orders_impl", "target": "convergence_scatter", "relation": "calls", "confidence": "EXTRACTED", "source_file": "src/plots/convergence.jl", "source_location": "L394", "weight": 1.0}, {"source": "convergence_interactive_pointwise_wave_convergence_orders_impl", "target": "convergence_display", "relation": "calls", "confidence": "EXTRACTED", "source_file": "src/plots/convergence.jl", "source_location": "L399", "weight": 1.0}]}